mcp_telegram/__init__.py
mcp_telegram/cli.py
mcp_telegram/server.py
mcp_telegram/telegram.py
mcp_telegram/types.py
mcp_telegram/utils.py
mcp_telegram-0.1.11.dist-info/METADATA
mcp_telegram-0.1.11.dist-info/WHEEL
mcp_telegram-0.1.11.dist-info/entry_points.txt
mcp_telegram-0.1.11.dist-info/licenses/LICENSE
mcp_telegram-0.1.11.dist-info/RECORD
