Metadata-Version: 2.4
Name: mcp-telegram
Version: 0.1.11
Summary: MCP Server for Telegram
Project-URL: Repository, https://github.com/dryeab/mcp-telegram
Project-URL: Issues, https://github.com/dryeab/mcp-telegram/issues
Author: Yeabsira Driba
Maintainer-email: Yeabsira Driba <dryeab@gmail.com>
License: MIT
License-File: LICENSE
Keywords: automation,git,llm,mcp,telegram
Requires-Python: >=3.10
Requires-Dist: cryptg>=0.5.0.post0
Requires-Dist: mcp[cli]>=1.6.0
Requires-Dist: pydantic-settings>=2.8.1
Requires-Dist: pydantic>=2.11.1
Requires-Dist: rich>=14.0.0
Requires-Dist: telethon>=1.39.0
Requires-Dist: typer>=0.15.2
Requires-Dist: xdg-base-dirs>=6.0.2
